finagg/__init__.py
finagg/__main__.py
finagg/backend.py
finagg/frame.py
finagg/portfolio.py
finagg/ratelimit.py
finagg/testing.py
finagg/utils.py
finagg/bea/__init__.py
finagg/bea/_cli.py
finagg/bea/api.py
finagg/bea/sql.py
finagg/fred/__init__.py
finagg/fred/_cli.py
finagg/fred/sql.py
finagg/fred/api/__init__.py
finagg/fred/api/_api.py
finagg/fred/api/_category.py
finagg/fred/api/_release.py
finagg/fred/api/_series.py
finagg/fred/api/_source.py
finagg/fred/api/_tags.py
finagg/fred/feat/__init__.py
finagg/fred/feat/_raw.py
finagg/fred/feat/_refined.py
finagg/fundam/__init__.py
finagg/fundam/_cli.py
finagg/fundam/feat.py
finagg/fundam/sql.py
finagg/indices/__init__.py
finagg/indices/_cli.py
finagg/indices/api.py
finagg/indices/sql.py
finagg/sec/__init__.py
finagg/sec/_cli.py
finagg/sec/api.py
finagg/sec/sql.py
finagg/sec/feat/__init__.py
finagg/sec/feat/_raw.py
finagg/sec/feat/_refined/__init__.py
finagg/sec/feat/_refined/annual.py
finagg/sec/feat/_refined/quarterly.py
finagg/yfinance/__init__.py
finagg/yfinance/_cli.py
finagg/yfinance/api.py
finagg/yfinance/sql.py
finagg/yfinance/feat/__init__.py
finagg/yfinance/feat/_raw.py
finagg/yfinance/feat/_refined.py
finagg-1.0.2.dist-info/LICENSE
finagg-1.0.2.dist-info/METADATA
finagg-1.0.2.dist-info/WHEEL
finagg-1.0.2.dist-info/entry_points.txt
finagg-1.0.2.dist-info/top_level.txt
finagg-1.0.2.dist-info/RECORD
