Metadata-Version: 2.1
Name: finagg
Version: 1.0.2
Summary: Data aggregation with popular and free financial APIs.
Author: Andrew B.
License: Apache License
Project-URL: Repository, https://github.com/theOGognf/finagg
Project-URL: Documentation, https://theogognf.github.io/finagg/
Classifier: Development Status :: 3 - Alpha
Classifier: Intended Audience :: Science/Research
Classifier: Intended Audience :: Developers
Classifier: License :: OSI Approved :: Apache Software License
Classifier: Operating System :: POSIX
Classifier: Operating System :: Unix
Classifier: Programming Language :: Python :: 3.10
Classifier: Programming Language :: Python :: 3.11
Classifier: Topic :: Office/Business :: Financial :: Investment
Classifier: Topic :: Software Development
Classifier: Topic :: Scientific/Engineering
Classifier: Typing :: Typed
Requires-Python: >=3.10
License-File: LICENSE
Requires-Dist: beautifulsoup4 ==4.*
Requires-Dist: click ==8.*
Requires-Dist: pandas ==2.*
Requires-Dist: pandas-stubs ==2.*
Requires-Dist: python-dotenv ==0.21.*
Requires-Dist: requests ==2.*
Requires-Dist: requests-cache ==0.9.*
Requires-Dist: SQLAlchemy ==2.*
Requires-Dist: tqdm ==4.*
Requires-Dist: types-requests ==2.*
Requires-Dist: typing-extensions ==4.*
Requires-Dist: yfinance <0.2.29
Provides-Extra: dev
Requires-Dist: build[virtualenv] ; extra == 'dev'
Requires-Dist: mypy ; extra == 'dev'
Requires-Dist: pre-commit ; extra == 'dev'
Requires-Dist: pytest ; extra == 'dev'
Requires-Dist: pytest-cov ; extra == 'dev'
Requires-Dist: pytest-xdist ; extra == 'dev'
Requires-Dist: pytest-randomly ; extra == 'dev'
Requires-Dist: sphinx ; extra == 'dev'
Requires-Dist: tox ; extra == 'dev'
Requires-Dist: virtualenv ; extra == 'dev'
